printedcolors/__init__.py
printedcolors/colors.py
printedcolors/colours.py
printedcolors-1.0.0.dist-info/METADATA
printedcolors-1.0.0.dist-info/WHEEL
printedcolors-1.0.0.dist-info/top_level.txt
printedcolors-1.0.0.dist-info/RECORD
