Metadata-Version: 2.1
Name: printedcolors
Version: 1.0.0
Summary: Print with Colors!
Author: kokodev
Author-email: koko@kokodev.cc
License: MIT License
